resumebuilder/__init__.py
resumebuilder/cli/__init__.py
resumebuilder/cli/commands.py
resumebuilder/cli/main.py
resumebuilder/generators/__init__.py
resumebuilder/generators/pdf_generator.py
resumebuilder/models/__init__.py
resumebuilder/models/resume.py
resumebuilder/resources/__init__.py
resumebuilder/templates/__init__.py
resumebuilder/templates/template_manager.py
resumebuilder/utils/__init__.py
resumebuilder/utils/config.py
resumebuilder/utils/interactive_input.py
resumebuilder/utils/yaml_utils.py
resumebuilder-0.1.2.dist-info/LICENSE
resumebuilder-0.1.2.dist-info/METADATA
resumebuilder-0.1.2.dist-info/WHEEL
resumebuilder-0.1.2.dist-info/entry_points.txt
resumebuilder-0.1.2.dist-info/top_level.txt
resumebuilder-0.1.2.dist-info/RECORD
