Metadata-Version: 2.2
Name: resumebuilder
Version: 0.1.2
Summary: A professional resume and cover letter generator with templating and customization options
Home-page: https://github.com/iron-hope-shop/tools-resume
Author: Brad Jackson
Author-email: me@brad-jackson.com
Project-URL: Bug Tracker, https://github.com/iron-hope-shop/tools-resume/issues
Project-URL: Documentation, https://github.com/iron-hope-shop/tools-resume/blob/master/README.md
Project-URL: Source Code, https://github.com/iron-hope-shop/tools-resume
Keywords: resume,cv,cover letter,pdf,generator,template,job application
Classifier: Development Status :: 4 - Beta
Classifier: Environment :: Console
Classifier: Intended Audience :: End Users/Desktop
Classifier: License :: OSI Approved :: MIT License
Classifier: Natural Language :: English
Classifier: Operating System :: OS Independent
Classifier: Programming Language :: Python :: 3
Classifier: Programming Language :: Python :: 3.8
Classifier: Programming Language :: Python :: 3.9
Classifier: Programming Language :: Python :: 3.10
Classifier: Programming Language :: Python :: 3.11
Classifier: Programming Language :: Python :: 3.12
Classifier: Topic :: Office/Business
Classifier: Topic :: Text Processing :: Markup
Classifier: Topic :: Utilities
Requires-Python: >=3.8
License-File: LICENSE
Requires-Dist: PyYAML==6.0.1
Requires-Dist: click==8.1.3
Requires-Dist: reportlab==4.0.9
Requires-Dist: python-dotenv==1.0.0
Requires-Dist: rich==13.3.5
Requires-Dist: pydantic==1.10.8
Requires-Dist: faker==18.10.1
Requires-Dist: Pillow==10.2.0
Requires-Dist: pytest==7.3.1
Requires-Dist: pytest-cov==4.1.0
Requires-Dist: flake8==6.0.0
Requires-Dist: black==23.3.0
Provides-Extra: dev
Requires-Dist: pytest>=7.3.1; extra == "dev"
Requires-Dist: pytest-cov>=4.1.0; extra == "dev"
Requires-Dist: flake8>=6.0.0; extra == "dev"
Requires-Dist: black>=23.3.0; extra == "dev"
Requires-Dist: isort>=5.12.0; extra == "dev"
Requires-Dist: mypy>=1.3.0; extra == "dev"
Requires-Dist: build>=0.10.0; extra == "dev"
Requires-Dist: twine>=4.0.2; extra == "dev"
Dynamic: author
Dynamic: author-email
Dynamic: classifier
Dynamic: description
Dynamic: description-content-type
Dynamic: home-page
Dynamic: keywords
Dynamic: project-url
Dynamic: provides-extra
Dynamic: requires-dist
Dynamic: requires-python
Dynamic: summary
